hello_datap_component_base/__init__.py
hello_datap_component_base/base.py
hello_datap_component_base/cli.py
hello_datap_component_base/config.py
hello_datap_component_base/discover.py
hello_datap_component_base/logger.py
hello_datap_component_base/mns_client.py
hello_datap_component_base/oss_client.py
hello_datap_component_base/runner.py
hello_datap_component_base-0.2.3.dist-info/METADATA
hello_datap_component_base-0.2.3.dist-info/WHEEL
hello_datap_component_base-0.2.3.dist-info/entry_points.txt
hello_datap_component_base-0.2.3.dist-info/top_level.txt
hello_datap_component_base-0.2.3.dist-info/RECORD
