Metadata-Version: 2.4
Name: hello-datap-component-base
Version: 0.2.3
Summary: A unified server management framework for data processing component
Author-email: zhaohaidong <zhaohaidong389@hellobike.com>
License: MIT
Project-URL: Homepage, https://gitlab.hellorobotaxi.top/hdata/hello-datap-component-base
Keywords: data,hello,management,microservice
Classifier: Development Status :: 4 - Beta
Classifier: Intended Audience :: Developers
Classifier: License :: OSI Approved :: MIT License
Classifier: Operating System :: OS Independent
Classifier: Programming Language :: Python :: 3
Classifier: Programming Language :: Python :: 3.8
Classifier: Programming Language :: Python :: 3.9
Classifier: Programming Language :: Python :: 3.10
Classifier: Programming Language :: Python :: 3.11
Classifier: Topic :: Software Development :: Libraries :: Application Frameworks
Requires-Python: >=3.8
Requires-Dist: click>=8.0.0
Requires-Dist: pydantic>=2.0.0
Requires-Dist: python-json-logger>=2.0.0
Requires-Dist: pyyaml>=6.0.0
Requires-Dist: aliyun-mns>=1.1.5
Requires-Dist: oss2>=2.18.0
Provides-Extra: dev
Requires-Dist: pytest>=7.0.0; extra == "dev"
Requires-Dist: black>=23.0.0; extra == "dev"
Requires-Dist: mypy>=1.0.0; extra == "dev"
